PracticePackage/__init__.py
PracticePackage/perceptron.py
PyPi_SutirthaSahu-0.0.1.dist-info/LICENSE
PyPi_SutirthaSahu-0.0.1.dist-info/METADATA
PyPi_SutirthaSahu-0.0.1.dist-info/WHEEL
PyPi_SutirthaSahu-0.0.1.dist-info/top_level.txt
PyPi_SutirthaSahu-0.0.1.dist-info/RECORD
