Metadata-Version: 2.1
Name: PyPi-SutirthaSahu
Version: 0.0.1
Summary: Its an implimentation of Perceptron
Home-page: https://github.com/SutirthaSahu/PyPi
Author: SutirthaSahu
Author-email: sutirthasahu@gmail.com
License: UNKNOWN
Project-URL: Bug Tracker, https://github.com/SutirthaSahu/PyPi/issues
Platform: UNKNOWN
Classifier: Programming Language :: Python :: 3
Classifier: License :: OSI Approved :: MIT License
Classifier: Operating System :: OS Independent
Requires-Python: >=3.7
License-File: LICENSE
Requires-Dist: numpy
Requires-Dist: tqdm
